ns_helper_functions.py
ns_helper_functions-0.0.8.dist-info/METADATA
ns_helper_functions-0.0.8.dist-info/WHEEL
ns_helper_functions-0.0.8.dist-info/top_level.txt
ns_helper_functions-0.0.8.dist-info/RECORD
