Metadata-Version: 2.2
Name: ns_helper_functions
Version: 0.0.8
Summary: helper functions commonly used in nornir and relative projects
Author-email: nstamoul <nstamoul0@gmail.com>
Project-URL: homepage, https://github.com/nstamoul/ns_helper_functions
Project-URL: repository, https://github.com/nstamoul/ns_helper_functions
Keywords: nornir,workbook,worksheet,nautobot,inventory,vault
Requires-Python: >=3.8
Requires-Dist: openpyxl>=3.1.5
Requires-Dist: rich>=13.9.4
Requires-Dist: pynautobot>=2.6.1
Requires-Dist: nornir>=3.5.0
Requires-Dist: ciscoconfparse
Requires-Dist: netmiko>=3.1.0
Requires-Dist: paramiko>=2.6.0
Requires-Dist: ciscoisesdk
Requires-Dist: pandas
